teamhack_recond/__init__.py
teamhack_recond/__main__.py
teamhack_recond/server.py
teamhack_recond/sql.py
teamhack_recond/util.py
teamhack_recond-0.0.818.dist-info/METADATA
teamhack_recond-0.0.818.dist-info/WHEEL
teamhack_recond-0.0.818.dist-info/top_level.txt
teamhack_recond-0.0.818.dist-info/RECORD
