Metadata-Version: 2.1
Name: teamhack-recond
Version: 0.0.818
Summary: Hack the Box Team Support Services
Requires-Dist: psycopg2
Requires-Dist: ratelimit
Requires-Dist: requests
Requires-Dist: teamhack-db
Provides-Extra: rel
Requires-Dist: twine ; extra == 'rel'
Provides-Extra: test
Requires-Dist: coverage ; extra == 'test'
Requires-Dist: pytest ; extra == 'test'
